<root>
    <PINUS>
        <GATTUNG>PINUS</GATTUNG>
        <GATTUNG>ABIES</GATTUNG>
        <GATTUNG>TSUGA</GATTUNG>
        <GATTUNG>PSEUDOTSUGA</GATTUNG>
        <GATTUNG>LARIX</GATTUNG>
        <GATTUNG>CRYPTOMERIA</GATTUNG>
        <GATTUNG>PSEUDOLARIX</GATTUNG>
    </PINUS>
    <QUERCUS>
        <GATTUNG>QUERCUS</GATTUNG>
        <GATTUNG>CERRIS</GATTUNG>
        <GATTUNG>ILEX</GATTUNG>
        <GATTUNG>LITHOCARPUS</GATTUNG>
    </QUERCUS>
    <FAGUS>
        <GATTUNG>FAGUS</GATTUNG>
        <GATTUNG>CASTANEA</GATTUNG>
        <GATTUNG>NOBILIS</GATTUNG>
    </FAGUS>
    <PICEA>
        <GATTUNG>BUXUS</GATTUNG>
        <GATTUNG>SORBUS</GATTUNG>
        <GATTUNG>TILIA</GATTUNG>
        <GATTUNG>CALOCEDRUS</GATTUNG>
        <GATTUNG>ZELKOVA</GATTUNG>
        <GATTUNG>GINKGO</GATTUNG>
        <GATTUNG>SOPHORA</GATTUNG>
        <GATTUNG>KOELREUTERIA</GATTUNG>
        <GATTUNG>TETRADIUM</GATTUNG>
        <GATTUNG>RHAMNUS</GATTUNG>
        <GATTUNG>JUNIPERUS</GATTUNG>
        <GATTUNG>EUCOMMIA</GATTUNG>
        <GATTUNG>LIQUIDAMBAR</GATTUNG>
        <GATTUNG>TOONA</GATTUNG>
        <GATTUNG>AMELANCHIER</GATTUNG>
        <GATTUNG>SAMBUCUS</GATTUNG>
        <GATTUNG>FRAXINUS</GATTUNG>
        <GATTUNG>WISTERIA</GATTUNG>
        <GATTUNG>COTINUS</GATTUNG>
        <GATTUNG>CERCIS</GATTUNG>
        <GATTUNG>NOTHOFAGUS</GATTUNG>
        <GATTUNG>SEQUOIADENDRON</GATTUNG>
        <GATTUNG>SYRINGA</GATTUNG>
        <GATTUNG>NYSSA</GATTUNG>
        <GATTUNG>CARPINUS</GATTUNG>
        <GATTUNG>HAMAMELIS</GATTUNG>
        <GATTUNG>PARROTIA</GATTUNG>
        <GATTUNG>OXYDENDRUM</GATTUNG>
        <GATTUNG>CEDRUS</GATTUNG>
        <GATTUNG>CELTIS</GATTUNG>
        <GATTUNG>ACER</GATTUNG>
        <GATTUNG>GYMNOCLADUS</GATTUNG>
        <GATTUNG>LIRIODENDRON</GATTUNG>
        <GATTUNG>CRATAEGUS</GATTUNG>
        <GATTUNG>PYRUS</GATTUNG>
        <GATTUNG>CEPHALOTAXUS</GATTUNG>
        <GATTUNG>PLATANUS</GATTUNG>
        <GATTUNG>AESCULUS</GATTUNG>
        <GATTUNG>TROCHODENDRON</GATTUNG>
        <GATTUNG>ULMUS</GATTUNG>
        <GATTUNG>UNBEKANNT</GATTUNG>
        <GATTUNG>OSTRYA</GATTUNG>
        <GATTUNG>ELAEAGNUS</GATTUNG>
        <GATTUNG>ROBINIA</GATTUNG>
        <GATTUNG>RHUS</GATTUNG>
        <GATTUNG>CARYA</GATTUNG>
        <GATTUNG>TAMARIX</GATTUNG>
        <GATTUNG>POPULUS</GATTUNG>
        <GATTUNG>MAGNOLIA</GATTUNG>
        <GATTUNG>METASEQUOIA</GATTUNG>
        <GATTUNG>MESPILUS</GATTUNG>
        <GATTUNG>PAULOWNIA</GATTUNG>
        <GATTUNG>MALUS</GATTUNG>
        <GATTUNG>PEROVSKIA</GATTUNG>
        <GATTUNG>BIOTA</GATTUNG>
        <GATTUNG>CORNUS</GATTUNG>
        <GATTUNG>THUJA</GATTUNG>
        <GATTUNG>STYRAX</GATTUNG>
        <GATTUNG>CARAGANA</GATTUNG>
        <GATTUNG>DAVIDIA</GATTUNG>
        <GATTUNG>LABURNUM</GATTUNG>
        <GATTUNG>HIPPOPHAE</GATTUNG>
        <GATTUNG>EUONYMUS</GATTUNG>
        <GATTUNG>LONICERA</GATTUNG>
        <GATTUNG>AILANTHUS</GATTUNG>
        <GATTUNG>CERCIDIPHYLLUM</GATTUNG>
        <GATTUNG>CLADRASTIS</GATTUNG>
        <GATTUNG>CHAMAECYPARIS</GATTUNG>
        <GATTUNG>CYDONIA</GATTUNG>
        <GATTUNG>PHELLODENDRON</GATTUNG>
        <GATTUNG>PTELEA</GATTUNG>
        <GATTUNG>CUPRESSOCYPARIS</GATTUNG>
        <GATTUNG>GLEDITSIA</GATTUNG>
        <GATTUNG>PTEROCARYA</GATTUNG>
        <GATTUNG>UNBEKANNT</GATTUNG>
        <GATTUNG>CUPRESSUS</GATTUNG>
        <GATTUNG>THUJOPSIS</GATTUNG>
        <GATTUNG>PRUNUS</GATTUNG>
        <GATTUNG>ALNUS</GATTUNG>
        <GATTUNG>TAXUS</GATTUNG>
        <GATTUNG>SALIX</GATTUNG>
        <GATTUNG>CHIONANTHUS</GATTUNG>
        <GATTUNG>BETULA</GATTUNG>
        <GATTUNG>CORYLUS</GATTUNG>
        <GATTUNG>MORUS</GATTUNG>
        <GATTUNG>SEQUOIA</GATTUNG>
        <GATTUNG>JUGLANS</GATTUNG>
        <GATTUNG>CATALPA</GATTUNG>
        <GATTUNG>TAXODIUM</GATTUNG>
    </PICEA>
</root>